{"servicePack":[{"modes":"+-","signature":"21","ID":"study","version":"1.0"},{"modes":"+-","signature":"21","ID":"exchange","version":"1.0"}],"servers":[],"port":13050,"repoDirPath":"\/home\/lukas\/Documents\/ctno_prototype\/dlt4pi_tno\/uni\/TEMP","name":"uni","claims":[{"SHA1List":["bbb508182737f74579dda5e09319b74c549dc0da"],"derivFacts":[],"derivRules":[],"workFlowID":"*serviceCL*","query":{"mode":"+-","predicate":"exchange","terms":["file(\/home\/lukas\/Documents\/ctno_prototype\/dlt4pi_tno\/uni\/TEMP\/applicantInfo.json)","O"],"signature":"21"},"workFlowSHA1":"*serviceCL*","derivServices":[{"modes":"+-","signature":"21","ID":"exchange","version":"1.0"}],"qClaim":{"mode":"+-","predicate":"exchange","terms":["file(\/home\/lukas\/Documents\/ctno_prototype\/dlt4pi_tno\/uni\/TEMP\/applicantInfo.json)","false"],"signature":"21"}},{"SHA1List":["0778f31fc1fc3f7605c0e644980cf1f2294d07c4"],"derivFacts":[],"derivRules":[],"workFlowID":"*serviceCL*","query":{"mode":"+-","predicate":"exchange","terms":["file(\/home\/lukas\/Documents\/ctno_prototype\/dlt4pi_tno\/uni\/TEMP\/TEMP\/temp_2_applicantInfo.json)","Ok17"],"signature":"21"},"workFlowSHA1":"*serviceCL*","derivServices":[{"modes":"+-","signature":"21","ID":"exchange","version":"1.0"}],"qClaim":{"mode":"+-","predicate":"exchange","terms":["file(\/home\/lukas\/Documents\/ctno_prototype\/dlt4pi_tno\/uni\/TEMP\/TEMP\/temp_2_applicantInfo.json)","false"],"signature":"21"}},{"SHA1List":["0778f31fc1fc3f7605c0e644980cf1f2294d07c4"],"derivFacts":[],"derivRules":[],"workFlowID":"*serviceCL*","query":{"mode":"+-","predicate":"exchange","terms":["file(\/home\/lukas\/Documents\/ctno_prototype\/dlt4pi_tno\/uni\/TEMP\/TEMP\/temp_10_applicantInfo.json)","Ok17"],"signature":"21"},"workFlowSHA1":"*serviceCL*","derivServices":[{"modes":"+-","signature":"21","ID":"exchange","version":"1.0"}],"qClaim":{"mode":"+-","predicate":"exchange","terms":["file(\/home\/lukas\/Documents\/ctno_prototype\/dlt4pi_tno\/uni\/TEMP\/TEMP\/temp_10_applicantInfo.json)","false"],"signature":"21"}},{"SHA1List":["82ec6d1c5cd558527372535d55e32b0a487d0a36"],"derivFacts":[],"derivRules":[],"workFlowID":"*serviceCL*","query":{"mode":"+-","predicate":"study","terms":["file(\/home\/lukas\/Documents\/ctno_prototype\/dlt4pi_tno\/uni\/TEMP\/TEMP\/temp_5_applicantInfo3.json)","Ok"],"signature":"21"},"workFlowSHA1":"*serviceCL*","derivServices":[{"modes":"+-","signature":"21","ID":"study","version":"1.0"}],"qClaim":{"mode":"+-","predicate":"study","terms":["file(\/home\/lukas\/Documents\/ctno_prototype\/dlt4pi_tno\/uni\/TEMP\/TEMP\/temp_5_applicantInfo3.json)","false"],"signature":"21"}},{"SHA1List":["82ec6d1c5cd558527372535d55e32b0a487d0a36"],"derivFacts":[],"derivRules":[],"workFlowID":"*serviceCL*","query":{"mode":"+-","predicate":"study","terms":["file(\/home\/lukas\/Documents\/ctno_prototype\/dlt4pi_tno\/uni\/TEMP\/TEMP\/temp_6_applicantInfo3.json)","Ok"],"signature":"21"},"workFlowSHA1":"*serviceCL*","derivServices":[{"modes":"+-","signature":"21","ID":"study","version":"1.0"}],"qClaim":{"mode":"+-","predicate":"study","terms":["file(\/home\/lukas\/Documents\/ctno_prototype\/dlt4pi_tno\/uni\/TEMP\/TEMP\/temp_6_applicantInfo3.json)","false"],"signature":"21"}},{"SHA1List":["84ecadd56e365552e717eee2b77eb1ebfe45baba"],"derivFacts":[],"derivRules":[],"workFlowID":"*serviceCL*","query":{"mode":"+-","predicate":"exchange","terms":["file(\/home\/lukas\/Documents\/ctno_prototype\/dlt4pi_tno\/uni\/TEMP\/TEMP\/temp_4_applicantInfo3.json)","Ok"],"signature":"21"},"workFlowSHA1":"*serviceCL*","derivServices":[{"modes":"+-","signature":"21","ID":"exchange","version":"1.0"}],"qClaim":{"mode":"+-","predicate":"exchange","terms":["file(\/home\/lukas\/Documents\/ctno_prototype\/dlt4pi_tno\/uni\/TEMP\/TEMP\/temp_4_applicantInfo3.json)","false"],"signature":"21"}},{"SHA1List":["0778f31fc1fc3f7605c0e644980cf1f2294d07c4"],"derivFacts":[],"derivRules":[],"workFlowID":"*serviceCL*","query":{"mode":"+-","predicate":"study","terms":["file(\/home\/lukas\/Documents\/ctno_prototype\/dlt4pi_tno\/uni\/TEMP\/TEMP\/temp_8_applicantInfo.json)","Ok"],"signature":"21"},"workFlowSHA1":"*serviceCL*","derivServices":[{"modes":"+-","signature":"21","ID":"study","version":"1.0"}],"qClaim":{"mode":"+-","predicate":"study","terms":["file(\/home\/lukas\/Documents\/ctno_prototype\/dlt4pi_tno\/uni\/TEMP\/TEMP\/temp_8_applicantInfo.json)","false"],"signature":"21"}},{"SHA1List":["84ecadd56e365552e717eee2b77eb1ebfe45baba"],"derivFacts":[],"derivRules":[],"workFlowID":"*serviceCL*","query":{"mode":"+-","predicate":"study","terms":["file(\/home\/lukas\/Documents\/ctno_prototype\/dlt4pi_tno\/uni\/TEMP\/TEMP\/temp_3_applicantInfo3.json)","Ok"],"signature":"21"},"workFlowSHA1":"*serviceCL*","derivServices":[{"modes":"+-","signature":"21","ID":"study","version":"1.0"}],"qClaim":{"mode":"+-","predicate":"study","terms":["file(\/home\/lukas\/Documents\/ctno_prototype\/dlt4pi_tno\/uni\/TEMP\/TEMP\/temp_3_applicantInfo3.json)","false"],"signature":"21"}},{"SHA1List":["0778f31fc1fc3f7605c0e644980cf1f2294d07c4"],"derivFacts":[],"derivRules":[],"workFlowID":"*serviceCL*","query":{"mode":"+-","predicate":"study","terms":["file(\/home\/lukas\/Documents\/ctno_prototype\/dlt4pi_tno\/uni\/TEMP\/TEMP\/temp_1_applicantInfo.json)","Ok16"],"signature":"21"},"workFlowSHA1":"*serviceCL*","derivServices":[{"modes":"+-","signature":"21","ID":"study","version":"1.0"}],"qClaim":{"mode":"+-","predicate":"study","terms":["file(\/home\/lukas\/Documents\/ctno_prototype\/dlt4pi_tno\/uni\/TEMP\/TEMP\/temp_1_applicantInfo.json)","false"],"signature":"21"}},{"SHA1List":["82ec6d1c5cd558527372535d55e32b0a487d0a36"],"derivFacts":[],"derivRules":[],"workFlowID":"*serviceCL*","query":{"mode":"+-","predicate":"study","terms":["file(\/home\/lukas\/Documents\/ctno_prototype\/dlt4pi_tno\/uni\/TEMP\/TEMP\/temp_7_applicantInfo3.json)","Ok"],"signature":"21"},"workFlowSHA1":"*serviceCL*","derivServices":[{"modes":"+-","signature":"21","ID":"study","version":"1.0"}],"qClaim":{"mode":"+-","predicate":"study","terms":["file(\/home\/lukas\/Documents\/ctno_prototype\/dlt4pi_tno\/uni\/TEMP\/TEMP\/temp_7_applicantInfo3.json)","true"],"signature":"21"}},{"SHA1List":["0778f31fc1fc3f7605c0e644980cf1f2294d07c4"],"derivFacts":[],"derivRules":[],"workFlowID":"*serviceCL*","query":{"mode":"+-","predicate":"study","terms":["file(\/home\/lukas\/Documents\/ctno_prototype\/dlt4pi_tno\/uni\/TEMP\/TEMP\/temp_9_applicantInfo.json)","Ok16"],"signature":"21"},"workFlowSHA1":"*serviceCL*","derivServices":[{"modes":"+-","signature":"21","ID":"study","version":"1.0"}],"qClaim":{"mode":"+-","predicate":"study","terms":["file(\/home\/lukas\/Documents\/ctno_prototype\/dlt4pi_tno\/uni\/TEMP\/TEMP\/temp_9_applicantInfo.json)","false"],"signature":"21"}},{"SHA1List":["bbb508182737f74579dda5e09319b74c549dc0da"],"derivFacts":[],"derivRules":[],"workFlowID":"*serviceCL*","query":{"mode":"+-","predicate":"study","terms":["file(\/home\/lukas\/Documents\/ctno_prototype\/dlt4pi_tno\/uni\/TEMP\/applicantInfo.json)","O"],"signature":"21"},"workFlowSHA1":"*serviceCL*","derivServices":[{"modes":"+-","signature":"21","ID":"study","version":"1.0"}],"qClaim":{"mode":"+-","predicate":"study","terms":["file(\/home\/lukas\/Documents\/ctno_prototype\/dlt4pi_tno\/uni\/TEMP\/applicantInfo.json)","true"],"signature":"21"}},{"SHA1List":["bbb508182737f74579dda5e09319b74c549dc0da"],"derivFacts":[],"derivRules":[],"workFlowID":"*serviceCL*","query":{"mode":"+-","predicate":"study","terms":["file(TEMP\/applicantInfo.json)","Ok"],"signature":"21"},"workFlowSHA1":"*serviceCL*","derivServices":[{"modes":"+-","signature":"21","ID":"study","version":"1.0"}],"qClaim":{"mode":"+-","predicate":"study","terms":["file(TEMP\/applicantInfo.json)","true"],"signature":"21"}}],"workflows":[]}